{
	"ZhangQing":
	{
		"Hello":["在下是全真派大弟子徐長卿!@NT"],
		"Talk":["明明身為全真派大弟子的我..卻為情所困...@SD",
				"記憶中的那個女生,好像叫做紫萱...?@CF",
				"我的好兄弟是景天,景天的景,景天的天!@HP",
				"三生三世.....這難道是上天給我的考驗嗎?@CF",
				"誰是顧留芳?\n故劉芳我是顧留芳嗎?@CF"]
	},
	"ZhangYin":
	{
		"Hello":["在下是全真弟子蘇長胤!@NT"],
		"Talk":["我想要成為像大師兄一樣的人!@HP",
				"昨天師傅傳授的套路究竟是由下往上出招?還是由上往下呢?@CF",
				"聽說華山派的大弟子令狐沖,被師傅給逐出師門了?!@DB",
				"在這江湖亂世中,加入全真派究竟是正確的決定嗎?@CF",
				"師弟,趕緊去練功吧,別偷懶了!@AG"]
	},
	"ZhangZhen":
	{
		"Hello":["咳~咳~咳,發生了甚麼事?!@NT"],
		"Talk":["難道說長卿真的無法躲過此劫嗎?@CF",
				"哀...難道全真派就要毀在我的手中嗎?@CF",
				"倘若我派弟子會絕世神功,就能振興我全真教.@CF",
				"甚麼你竟然會降龍十八掌??@DB",
				"還不快去練功,想偷懶?門都沒有!@AG"]
	},
	"ZhangHen":
	{
		"Hello":["亨,廢話少說,有屁快放!@NT"],
		"Talk":["亨...師傅只關注大師兄,從不在意其他師兄弟的死活!@CF",
				"看甚麼看全真教就是收了你這種人,才會如此不堪.@CF",
				"你可以閃邊站嗎?有夠討人厭!@CF",
				"我想要一步一步的往上爬,讓天下人的信服我的力量.@AG",
				"喂!究竟是誰教你降龍十八掌的?去,肯定是從哪偷學來的.@CF"]
	},
	"ZhangFong":
	{
		"Hello":["人生在世,\n事事難料阿,\n兄弟,我這詩吟得如何?!@HP"],
		"Talk":["對酒當歌,人生幾何?譬如朝露,去日苦多.@CF",
				"我無欲無求,喝得暖,吃得飽就行了!@HP",
				"兄弟喜歡吟詩嗎?@HP",
				"今朝有酒今朝醉,明日愁來明日愁.@HP",
				"天之道，損有餘而補不足...聽說是神功秘笈的開頭!@CF"]
	},
	"ZhangWo":
	{
		"Hello":["咳~咳~咳,孔子說過四十而不惑，五十而知天命...看來我已到了知天命之時...!@HP"],
		"Talk":["待在全真教三十年,卻仍然沒有甚麼長進...@SD",
				"從前的全真教....\n哀~不說了...!@CF",
				"很好~很好~\n很好啊~~~~@HP",
				"你小小年紀內功竟如此深厚...@DB",
				"咳~咳~咳,又咳出血了...@BL"]
	}
}